{
  "title": "Universal Target for applications",
  "description": "Node application build target options for Build Facade",
  "type": "object",
  "properties": {
    "watch": {
      "type": "boolean",
      "default": true
    },
    "browserTarget": {
      "type": "string",
      "description": "The target to build a browser bundle"
    },
    "universalTarget": {
      "type": "string",
      "description": "The target to build a universal bundle"
    },
    "ssrExecuteTarget": {
      "type": "string",
      "description": "The target to start your SSR Nodejs server"
    }
  },
  "additionalProperties": false,
  "required": ["browserTarget", "universalTarget", "ssrExecuteTarget"]
}